hwp2yaml/__init__.py
hwp2yaml/batch.py
hwp2yaml/cli.py
hwp2yaml/constants.py
hwp2yaml/exporter.py
hwp2yaml/extractor.py
hwp2yaml/hwp3_converter.py
hwp2yaml/models.py
hwp2yaml/reader.py
hwp2yaml/record.py
hwp2yaml/structure.py
hwp2yaml/triage.py
hwp2yaml/utils.py
hwp2yaml-0.6.1.dist-info/METADATA
hwp2yaml-0.6.1.dist-info/WHEEL
hwp2yaml-0.6.1.dist-info/entry_points.txt
hwp2yaml-0.6.1.dist-info/licenses/LICENSE
hwp2yaml-0.6.1.dist-info/RECORD
