Metadata-Version: 2.4
Name: hwp2yaml
Version: 0.6.1
Summary: HWP 5.x / HWPX / HWP 3.x to YAML converter with structure preservation
Project-URL: Homepage, https://github.com/seunghyuoffice-design/hwp2yaml
Project-URL: Repository, https://github.com/seunghyuoffice-design/hwp2yaml.git
Author: Dyarchy Project
License-Expression: MIT
License-File: LICENSE
Keywords: converter,document,hanword,hwp,hwpx,korean,yaml
Classifier: Development Status :: 4 - Beta
Classifier: Intended Audience :: Developers
Classifier: License :: OSI Approved :: MIT License
Classifier: Programming Language :: Python :: 3
Classifier: Programming Language :: Python :: 3.10
Classifier: Programming Language :: Python :: 3.11
Classifier: Programming Language :: Python :: 3.12
Classifier: Topic :: Text Processing :: General
Requires-Python: >=3.10
Requires-Dist: olefile>=0.47
Requires-Dist: pyyaml>=6.0.3
Requires-Dist: tqdm>=4.67
Provides-Extra: dev
Requires-Dist: pytest-cov>=7.0; extra == 'dev'
Requires-Dist: pytest>=9.0; extra == 'dev'
Requires-Dist: ruff>=0.14.13; extra == 'dev'
